[
  {
    "inputs": [
      {
        "internalType": "string",
        "name": "_name",
        "type": "string"
      },
      {
        "internalType": "uint256",
        "name": "_id",
        "type": "uint256"
      },
      {
        "internalType": "string",
        "name": "_faculty",
        "type": "string"
      },
      {
        "internalType": "string",
        "name": "_department",
        "type": "string"
      },
      {
        "internalType": "uint256",
        "name": "_regYear",
        "type": "uint256"
      }
    ],
    "stateMutability": "nonpayable",
    "type": "constructor"
  },
  {
    "inputs": [
      {
        "internalType": "uint256",
        "name": "_termIndex",
        "type": "uint256"
      },
      {
        "internalType": "string",
        "name": "_courseName",
        "type": "string"
      },
      {
        "internalType": "uint256",
        "name": "_courseID",
        "type": "uint256"
      },
      {
        "internalType": "string",
        "name": "_courseCode",
        "type": "string"
      },
      {
        "internalType": "string",
        "name": "_instructor",
        "type": "string"
      },
      {
        "internalType": "uint256",
        "name": "_credit",
        "type": "uint256"
      },
      {
        "internalType": "uint256",
        "name": "_evalCount",
        "type": "uint256"
      },
      {
        "internalType": "string[]",
        "name": "_evalNames",
        "type": "string[]"
      },
      {
        "internalType": "uint256[]",
        "name": "_evalWeights",
        "type": "uint256[]"
      }
    ],
    "name": "addCourse",
    "outputs": [],
    "stateMutability": "nonpayable",
    "type": "function"
  },
  {
    "inputs": [
      {
        "internalType": "uint256",
        "name": "_year",
        "type": "uint256"
      },
      {
        "internalType": "string",
        "name": "_season",
        "type": "string"
      }
    ],
    "name": "addTerm",
    "outputs": [],
    "stateMutability": "nonpayable",
    "type": "function"
  },
  {
    "inputs": [],
    "name": "department",
    "outputs": [
      {
        "internalType": "string",
        "name": "",
        "type": "string"
      }
    ],
    "stateMutability": "view",
    "type": "function"
  },
  {
    "inputs": [],
    "name": "faculty",
    "outputs": [
      {
        "internalType": "string",
        "name": "",
        "type": "string"
      }
    ],
    "stateMutability": "view",
    "type": "function"
  },
  {
    "inputs": [],
    "name": "getDepartment",
    "outputs": [
      {
        "internalType": "string",
        "name": "",
        "type": "string"
      }
    ],
    "stateMutability": "view",
    "type": "function"
  },
  {
    "inputs": [],
    "name": "getFaculty",
    "outputs": [
      {
        "internalType": "string",
        "name": "",
        "type": "string"
      }
    ],
    "stateMutability": "view",
    "type": "function"
  },
  {
    "inputs": [],
    "name": "getID",
    "outputs": [
      {
        "internalType": "uint256",
        "name": "",
        "type": "uint256"
      }
    ],
    "stateMutability": "view",
    "type": "function"
  },
  {
    "inputs": [],
    "name": "getName",
    "outputs": [
      {
        "internalType": "string",
        "name": "",
        "type": "string"
      }
    ],
    "stateMutability": "view",
    "type": "function"
  },
  {
    "inputs": [],
    "name": "getRegYear",
    "outputs": [
      {
        "internalType": "uint256",
        "name": "",
        "type": "uint256"
      }
    ],
    "stateMutability": "view",
    "type": "function"
  },
  {
    "inputs": [],
    "name": "getTerms",
    "outputs": [
      {
        "internalType": "contract Term[]",
        "name": "",
        "type": "address[]"
      }
    ],
    "stateMutability": "view",
    "type": "function"
  },
  {
    "inputs": [],
    "name": "name",
    "outputs": [
      {
        "internalType": "string",
        "name": "",
        "type": "string"
      }
    ],
    "stateMutability": "view",
    "type": "function"
  },
  {
    "inputs": [],
    "name": "regYear",
    "outputs": [
      {
        "internalType": "uint256",
        "name": "",
        "type": "uint256"
      }
    ],
    "stateMutability": "view",
    "type": "function"
  },
  {
    "inputs": [
      {
        "internalType": "uint256",
        "name": "_termIndex",
        "type": "uint256"
      },
      {
        "internalType": "uint256",
        "name": "_courseID",
        "type": "uint256"
      },
      {
        "internalType": "uint256",
        "name": "_evalIndex",
        "type": "uint256"
      },
      {
        "internalType": "uint256",
        "name": "_evalGrade",
        "type": "uint256"
      }
    ],
    "name": "setCourseEvalGrade",
    "outputs": [],
    "stateMutability": "nonpayable",
    "type": "function"
  },
  {
    "inputs": [
      {
        "internalType": "uint256",
        "name": "_termIndex",
        "type": "uint256"
      },
      {
        "internalType": "uint256",
        "name": "_courseID",
        "type": "uint256"
      },
      {
        "internalType": "string",
        "name": "_grade",
        "type": "string"
      },
      {
        "internalType": "string",
        "name": "_letterGrade",
        "type": "string"
      }
    ],
    "name": "setCourseOverallGrade",
    "outputs": [],
    "stateMutability": "nonpayable",
    "type": "function"
  },
  {
    "inputs": [
      {
        "internalType": "uint256",
        "name": "",
        "type": "uint256"
      }
    ],
    "name": "terms",
    "outputs": [
      {
        "internalType": "contract Term",
        "name": "",
        "type": "address"
      }
    ],
    "stateMutability": "view",
    "type": "function"
  }
]